pyglint/__init__.py
pyglint-0.1.3.dist-info/LICENSE
pyglint-0.1.3.dist-info/WHEEL
pyglint-0.1.3.dist-info/METADATA
pyglint-0.1.3.dist-info/RECORD
