Metadata-Version: 2.1
Name: pyglint
Version: 0.1.3
Summary: Pylint checkers made easy.
Author: metatooling
Author-email: metatooling@cordaz.com
Requires-Python: >=3.5,<4.0
Classifier: Programming Language :: Python :: 3
Classifier: Programming Language :: Python :: 3.5
Classifier: Programming Language :: Python :: 3.6
Classifier: Programming Language :: Python :: 3.7
Classifier: Programming Language :: Python :: 3.8
Provides-Extra: docs
Requires-Dist: attrs
Requires-Dist: public (>=2019.4.13,<2020.0.0)
Requires-Dist: pylint
